privex/__init__.py
privex/steem/SteemAsync.py
privex/steem/__init__.py
privex/steem/__main__.py
privex/steem/cli.py
privex/steem/exceptions.py
privex/steem/objects.py
privex/steem/benchmarks/__init__.py
privex/steem/benchmarks/bench_async.py
privex/steem/benchmarks/bench_beem.py
steem_async-2.1.0.dist-info/LICENSE
steem_async-2.1.0.dist-info/METADATA
steem_async-2.1.0.dist-info/WHEEL
steem_async-2.1.0.dist-info/top_level.txt
steem_async-2.1.0.dist-info/RECORD
