Metadata-Version: 2.1
Name: steem-async
Version: 2.1.0
Summary: A simple Python library for asynchronous interactions with Hive/Steem RPC nodes (and forks)
Home-page: https://github.com/Privex/steem-async
Author: Chris (Someguy123) @ Privex
Author-email: chris@privex.io
License: MIT
Platform: UNKNOWN
Classifier: Programming Language :: Python :: 3
Classifier: Programming Language :: Python :: 3.7
Classifier: Programming Language :: Python :: 3.8
Classifier: Programming Language :: Python :: 3.9
Classifier: License :: OSI Approved :: MIT License
Classifier: Operating System :: OS Independent
License-File: LICENSE
Requires-Dist: httpx[http2] (>=0.7)
Requires-Dist: privex-helpers (>=3.0.0)
Requires-Dist: async-property (>=0.2.1)
Requires-Dist: rich
Provides-Extra: bench
Requires-Dist: beem ; extra == 'bench'
